nonebot/adapters/chaoxing/__init__.py
nonebot/adapters/chaoxing/adapter.py
nonebot/adapters/chaoxing/bot.py
nonebot/adapters/chaoxing/config.py
nonebot/adapters/chaoxing/event.py
nonebot/adapters/chaoxing/exception.py
nonebot/adapters/chaoxing/message.py
nonebot/adapters/chaoxing/utils.py
nonebot/adapters/chaoxing/res/im.html
nonebot_adapter_chaoxing-0.0.8.dist-info/LICENSE
nonebot_adapter_chaoxing-0.0.8.dist-info/METADATA
nonebot_adapter_chaoxing-0.0.8.dist-info/WHEEL
nonebot_adapter_chaoxing-0.0.8.dist-info/top_level.txt
nonebot_adapter_chaoxing-0.0.8.dist-info/RECORD
