Metadata-Version: 2.2
Name: nonebot-adapter-chaoxing
Version: 0.0.8
Summary: Nonebot2 Adapter for 超星学习通
Author-email: YangRucheng <admin@yangrucheng.top>
License: MIT
Project-URL: homepage, https://github.com/YangRucheng/nonebot-adapter-chaoxing
Project-URL: repository, https://github.com/YangRucheng/nonebot-adapter-chaoxing
Requires-Python: >=3.10
License-File: LICENSE
Requires-Dist: nonebot2>=2.3.0
Requires-Dist: httpx>=0.28.0
